accelbyte_py_sdk/api/reporting/__init__.py
accelbyte_py_sdk/api/reporting/errors.py
accelbyte_py_sdk/api/reporting/models/__init__.py
accelbyte_py_sdk/api/reporting/models/restapi_action_api_request.py
accelbyte_py_sdk/api/reporting/models/restapi_action_api_response.py
accelbyte_py_sdk/api/reporting/models/restapi_action_list_api_response.py
accelbyte_py_sdk/api/reporting/models/restapi_admin_all_reasons_response.py
accelbyte_py_sdk/api/reporting/models/restapi_admin_reason_list_response.py
accelbyte_py_sdk/api/reporting/models/restapi_admin_reason_response.py
accelbyte_py_sdk/api/reporting/models/restapi_ban_account_action_request.py
accelbyte_py_sdk/api/reporting/models/restapi_ban_account_action_response.py
accelbyte_py_sdk/api/reporting/models/restapi_category_limit.py
accelbyte_py_sdk/api/reporting/models/restapi_config_response.py
accelbyte_py_sdk/api/reporting/models/restapi_create_reason_group_request.py
accelbyte_py_sdk/api/reporting/models/restapi_create_reason_request.py
accelbyte_py_sdk/api/reporting/models/restapi_error_response.py
accelbyte_py_sdk/api/reporting/models/restapi_extension_category_api_request.py
accelbyte_py_sdk/api/reporting/models/restapi_extension_category_api_response.py
accelbyte_py_sdk/api/reporting/models/restapi_extension_category_list_api_response.py
accelbyte_py_sdk/api/reporting/models/restapi_moderation_rule_actions_request.py
accelbyte_py_sdk/api/reporting/models/restapi_moderation_rule_actions_response.py
accelbyte_py_sdk/api/reporting/models/restapi_moderation_rule_active_request.py
accelbyte_py_sdk/api/reporting/models/restapi_moderation_rule_request.py
accelbyte_py_sdk/api/reporting/models/restapi_moderation_rule_response.py
accelbyte_py_sdk/api/reporting/models/restapi_moderation_rules_list.py
accelbyte_py_sdk/api/reporting/models/restapi_pagination.py
accelbyte_py_sdk/api/reporting/models/restapi_public_reason_group_response.py
accelbyte_py_sdk/api/reporting/models/restapi_public_reason_list_response.py
accelbyte_py_sdk_service_reporting-0.21.0.dist-info/METADATA
accelbyte_py_sdk_service_reporting-0.21.0.dist-info/WHEEL
accelbyte_py_sdk_service_reporting-0.21.0.dist-info/top_level.txt
accelbyte_py_sdk_service_reporting-0.21.0.dist-info/RECORD
