Metadata-Version: 2.4
Name: accelbyte-py-sdk-service-reporting
Version: 0.21.0
Summary: AccelByte Python SDK - AccelByte Gaming Services Reporting Service
Requires-Python: >=3.9
Requires-Dist: accelbyte-py-sdk-core
